rlhelper/__init__.py
rlhelper/main.py
rlhelper2-0.1.dist-info/METADATA
rlhelper2-0.1.dist-info/WHEEL
rlhelper2-0.1.dist-info/top_level.txt
rlhelper2-0.1.dist-info/RECORD
