Metadata-Version: 2.1
Name: rlhelper2
Version: 0.1
Summary: A small RL helper function for reward normalization
Author: Devaansh Shukla
